{"is_source_file": true, "format": "Dart", "description": "This file serves as the entry point for a Flutter-based dictionary app. It initializes the app with a custom theme and renders the initial search page.", "external_files": ["src/pages/search_page.dart", "src/theme/ocean_theme.dart"], "external_methods": ["runApp", "buildOceanTheme"], "published": ["main"], "classes": [{"name": "DictionaryApp", "description": "A root widget for the app that applies the Ocean Professional theme and builds the main MaterialApp."}], "methods": [{"name": "main", "description": "The entry point that runs the DictionaryApp widget."}, {"name": "build", "description": "Builds the MaterialApp with title, theme, and home page."}], "calls": ["runApp", "buildOceanTheme"], "search-terms": ["main.dart", "Flutter app entry point", "DictionaryApp", "Ocean theme", "SearchPage", "MaterialApp"], "state": 2, "file_id": 3, "knowledge_revision": 38, "git_revision": "", "revision_history": [{"26": ""}, {"38": ""}], "hash": "5b1880ab4feb6ed50ece045250887b44", "format-version": 4, "code-base-name": "dictionary_frontend", "filename": "dictionary_frontend/lib/main.dart"}